storage_cache/__init__.py
storage_cache/excepts.py
storage_cache/main.py
storage_cache/types.py
storage_cache/cache/__init__.py
storage_cache/cache/redis_cache.py
storage_cache/util/__init__.py
storage_cache/util/config.py
storage_cache-1.1.2.dist-info/LICENSE
storage_cache-1.1.2.dist-info/METADATA
storage_cache-1.1.2.dist-info/WHEEL
storage_cache-1.1.2.dist-info/top_level.txt
storage_cache-1.1.2.dist-info/RECORD
